poolhub/__init__.py
poolhub/main.py
poolhub/frontend/__init__.py
poolhub/frontend/utils.py
poolhub/frontend/poolhub-app/dist/favicon.ico
poolhub/frontend/poolhub-app/dist/index.html
poolhub/frontend/poolhub-app/dist/inline.bundle.js
poolhub/frontend/poolhub-app/dist/inline.bundle.js.map
poolhub/frontend/poolhub-app/dist/main.bundle.js
poolhub/frontend/poolhub-app/dist/main.bundle.js.map
poolhub/frontend/poolhub-app/dist/polyfills.bundle.js
poolhub/frontend/poolhub-app/dist/polyfills.bundle.js.map
poolhub/frontend/poolhub-app/dist/styles.bundle.js
poolhub/frontend/poolhub-app/dist/styles.bundle.js.map
poolhub/frontend/poolhub-app/dist/vendor.bundle.js
poolhub/frontend/poolhub-app/dist/vendor.bundle.js.map
poolhub/server/__init__.py
poolhub/server/server.py
poolhub/server/__pycache__/__init__.cpython-35.pyc
poolhub/server/__pycache__/server.cpython-35.pyc
poolhub/threads/__init__.py
poolhub/threads/thread_tree.py
poolhub/threads/threader.py
poolhub/threads/threadsAPI.py
poolhub/threads/__pycache__/__init__.cpython-35.pyc
poolhub/threads/__pycache__/thread_tree.cpython-35.pyc
poolhub/threads/__pycache__/threader.cpython-35.pyc
poolhub/threads/__pycache__/threadsAPI.cpython-35.pyc
poolhub-0.0.9.dist-info/DESCRIPTION.rst
poolhub-0.0.9.dist-info/METADATA
poolhub-0.0.9.dist-info/RECORD
poolhub-0.0.9.dist-info/WHEEL
poolhub-0.0.9.dist-info/metadata.json
poolhub-0.0.9.dist-info/top_level.txt
