Metadata-Version: 2.0
Name: poolhub
Version: 0.0.9
Summary: Track threads in your Python program.
Home-page: https://github.com/tsarpaul/poolhub
Author: Paul Litvak
Author-email: litvakpol@012.net.il
License: MIT License
Keywords: multithreading,python,tool
Platform: UNKNOWN
Requires-Dist: aiohttp
Requires-Dist: aiohttp-cors
Requires-Dist: python-socketio
